daskqueue/ActorPool.py
daskqueue/Consumer.py
daskqueue/ConsumerPool.py
daskqueue/Protocol.py
daskqueue/QueuePool.py
daskqueue/__init__.py
daskqueue/_version.py
daskqueue/backend.py
daskqueue/queue/__init__.py
daskqueue/queue/base_queue.py
daskqueue/queue/durable_queue.py
daskqueue/queue/queue_exceptions.py
daskqueue/queue/sql_queue.py
daskqueue/queue/transient_queue.py
daskqueue/segment/__init__.py
daskqueue/segment/index_record.py
daskqueue/segment/index_segment.py
daskqueue/segment/log_record.py
daskqueue/segment/log_segment.py
daskqueue/utils/__init__.py
daskqueue/utils/funcs.py
daskqueue/utils/logger.py
daskqueue/utils/start_cluster.py
daskqueue-0.2.0.dist-info/LICENSE.md
daskqueue-0.2.0.dist-info/METADATA
daskqueue-0.2.0.dist-info/WHEEL
daskqueue-0.2.0.dist-info/top_level.txt
daskqueue-0.2.0.dist-info/RECORD
