Metadata-Version: 2.1
Name: daskqueue
Version: 0.2.0
Summary: daskqueue distributed queue package
Home-page: UNKNOWN
Author: Amine Dirhoussi
Maintainer-email: aminedirhoussi1@gmail.com
License: MIT
Project-URL: Source, https://github.com/AmineDiro/daskqueue/
Keywords: Distributed Task Queue
Platform: UNKNOWN
Classifier: Development Status :: 3 - Alpha
Classifier: Intended Audience :: Developers
Classifier: Topic :: Software Development :: Build Tools
Classifier: License :: OSI Approved :: MIT License
Classifier: Programming Language :: Python :: 3
Classifier: Programming Language :: Python :: 3.6
Classifier: Programming Language :: Python :: 3.7
Classifier: Programming Language :: Python :: 3.8
Classifier: Programming Language :: Python :: 3.9
Requires-Python: >3.6
License-File: LICENSE.md
Requires-Dist: numpy
Requires-Dist: dask (>=2022.7.1)
Requires-Dist: distributed (>=2022.7.1)
